ysdtools/__init__.py
ysdtools/ysdlog.py
ysdtools-0.1.1.dist-info/LICENSE
ysdtools-0.1.1.dist-info/WHEEL
ysdtools-0.1.1.dist-info/METADATA
ysdtools-0.1.1.dist-info/RECORD
