Metadata-Version: 2.1
Name: ysdtools
Version: 0.1.1
Summary: A collection of useful python tools
Author: ysd
Author-email: helloysd@foxmail.com
Requires-Python: >3.7,<4.0
Classifier: Programming Language :: Python :: 3
Classifier: Programming Language :: Python :: 3.8
Classifier: Programming Language :: Python :: 3.9
